Lab8/Ejercicio_3/Ejercicio_3.v
// Fredy Godoy - 19260
// Ejercicio 3 - ALU
module ALU(input logic [2:0]Seleccion,input [3:0]A,B,output [3:0]Output);
reg[3:0]Output;
always @(*) begin
case(Seleccion)
3'b000:  Output <= A & B;
3'b001:  Output <= A | B;
3'b010:  Output <= A + B;
3'b011:  Output <= 4'bxxxx;
3'b100:  Output <= A & ~B;
3'b101:  Output <=  A | ~B;
3'b110:  Output <= A - B;
3'b111:  Output <=  (A<B)? 1:0; 
default: Output = 4'bxxxx;
endcase
end
endmodule

Lab8/Ejercicio_3/Ejercicio_3_tb.v

// Fredy Godoy - 19260
// Testbench Ejercicio 3 - ALU

module testbench();
reg [2:0]seleccion;
reg [3:0] a,b;
wire [3:0]Output;

ALU alu(seleccion, a, b, Output);

initial begin 
$display ("ALU de 4 bits");
$display (" Seleción  | A  |  B  |  Salida");
$display ("-----------|----|-----|--------");
$monitor ("    %b       %b    %b      %b",seleccion, a, b, Output);


#1 seleccion=3'b000; a=4'b0110; b=4'b0001; 
#1 seleccion=3'b001; a=4'b0110; b=4'b0001;
#1 seleccion=3'b010; a=4'b0110; b=4'b0001;
#1 seleccion=3'b011; a=4'b0110; b=4'b0001;
#1 seleccion=3'b100; a=4'b0110; b=4'b0001;
#1 seleccion=3'b101; a=4'b0110; b=4'b0001;
#1 seleccion=3'b110; a=4'b0110; b=4'b0001;
#1 seleccion=3'b111; a=4'b0110; b=4'b0001;
#1 seleccion=3'b111; a=4'b0110; b=4'b1111;
#1 seleccion=3'b111; a=4'b0001; b=4'b0001;
end
initial
#100 $finish;
initial begin 
$dumpfile ("Ejercicio_3_tb.vcd");
$dumpvars(0,testbench);
end
endmodule

Lab8/Ejercicio_3/Ejercicio_3_tb.vcd
$date
	Sat Oct 24 23:10:23 2020
$end
$version
	Icarus Verilog
$end
$timescale
	1ps
$end
$scope module testbench $end
$var wire 4 ! Output [3:0] $end
$var reg 4 " a [3:0] $end
$var reg 4 # b [3:0] $end
$var reg 3 $ seleccion [2:0] $end
$scope module alu $end
$var wire 4 % A [3:0] $end
$var wire 4 & B [3:0] $end
$var wire 3 ' Seleccion [2:0] $end
$var reg 4 ( Output [3:0] $end
$upscope $end
$upscope $end
$enddefinitions $end
#0
$dumpvars
bx (
bx '
bx &
bx %
bx $
bx #
bx "
bx !
$end
#1
b0 !
b0 (
b1 #
b1 &
b110 "
b110 %
b0 $
b0 '
#2
b111 !
b111 (
b1 $
b1 '
#3
b10 $
b10 '
#4
bx !
bx (
b11 $
b11 '
#5
b110 !
b110 (
b100 $
b100 '
#6
b1110 !
b1110 (
b101 $
b101 '
#7
b101 !
b101 (
b110 $
b110 '
#8
b0 !
b0 (
b111 $
b111 '
#9
b1 !
b1 (
b1111 #
b1111 &
#10
b0 !
b0 (
b1 #
b1 &
b1 "
b1 %
