Lab6/Ejercicio 6/Lab6_E6.v
//Fredy Godoy 19260

//Ejercicio no.6 - Laboratorio no.6

module FFD(input logic clk, input logic reset,input logic set, input logic [3:0]D, output [3:0]Q);
reg Q;
always @ (posedge clk or posedge reset)
if (reset) begin
Q<= 4'b0000;
end else if (set)begin
Q<= 4'b1111;
end else begin
Q<= D;
end
endmodule

module ejercicio1(input wire A, B, input logic clk, reset, set, output Y);

output [1:0]D;
output [1:0]Q;
FFD U1(clk, D, reset, set, Q);
assign D[0] = (~Q[1] & ~Q[0] & A);
assign D[1] = (Q[0] & B)|(Q[1] & A & B);
assign Y= (Q[1] & A & B);

endmodule

Lab6/Ejercicio 6/Lab6_E6_tb.v


module testbench();

reg clk,reset, A, B, set;
wire Y;
//reg [1:0]E;

ejercicio1 U1(A,B,clk, reset, set, Y);
initial begin
clk=0;
forever #1 clk=~clk;
end

initial begin 
#3 
$display("\n");
$display("clk reset A B SF SP | Y)");
$monitor("%b %b %b | %b", clk, A , B, Y);


reset=1; A=0; B=0; set=0;
#1 reset=0; A=0; B=0; 
#1 reset=0; A=0; B=0; 
#1 reset=0; A=1; B=0; 
#1 reset=0; A=1; B=1; 
#1 reset=0; A=1; B=0; 
#1 reset=0; A=1; B=0; 
#1 reset=0; A=1; B=0; 
#50 $finish;
end

 initial begin 
 $dumpfile("Lab6_E6_tb.vcd");
 $dumpvars(0,testbench);
 end
 endmodule

Lab6/Ejercicio 6/Lab6_E6_tb.vcd
$date
	Sat Sep 05 22:01:47 2020
$end
$version
	Icarus Verilog
$end
$timescale
	1ps
$end
$scope module testbench $end
$var wire 1 ! Y $end
$var reg 1 " A $end
$var reg 1 # B $end
$var reg 1 $ clk $end
$var reg 1 % reset $end
$var reg 1 & set $end
$scope module U1 $end
$var wire 1 " A $end
$var wire 1 # B $end
$var wire 1 ! Y $end
$var wire 1 $ clk $end
$var wire 1 % reset $end
$var wire 1 & set $end
$var wire 2 ' Q [1:0] $end
$var wire 2 ( D [1:0] $end
$scope module U1 $end
$var wire 4 ) D [3:0] $end
$var wire 1 $ clk $end
$var wire 1 * reset $end
$var wire 1 % set $end
$var reg 4 + Q [3:0] $end
$upscope $end
$upscope $end
$upscope $end
$enddefinitions $end
#0
$dumpvars
bx +
x*
b0x )
bx (
bx '
x&
x%
0$
x#
x"
x!
$end
#1
0!
b0x '
b0x +
1$
#2
0$
#3
b11 '
b1111 +
0*
b0 (
1$
b0 )
0&
0#
0"
1%
#4
0$
0%
#5
b0 '
b0 +
1$
#6
1*
b1 (
0$
1"
#7
1$
1#
#8
0$
0#
