Lab 3/Tabla3POS/Tabla3POS.v
module Tabla3POS();
	wire wAn, wBn, wCn, wDn, wo1, wo2, wo3, wo4, wo5, wo6,wo7, wo8, wo9, out; //w=wire "A" "B" "C" "D" n=not a=and o=or 
	reg A,B,C,D;
	
	not not1(wAn,A);
	not not2(wBn,B);
	not not3(wCn,C);
	not not4(wDn,D);
	or or1(wo1,A,wBn,C,D);
	or or2(wo2,A,wBn,C,wDn);
	or or3(wo3,A,wBn,wCn,D);
	or or4(wo4,A,wBn,wCn,wDn);
	or or5(wo5,wAn,B,C,wDn);
	or or6(wo6,wAn,B,wCn,wDn);
	or or7(wo7,wAn,wBn,C,D);
	or or8(wo8,wAn,wBn,C,wDn);
	or or9(wo9,wAn,wBn,wCn,wDn);
	and and1(out,wo1, wo2, wo3, wo4, wo5, wo6, wo7, wo8, wo9);

	
	initial begin 
		$display("A B C D| Y");
		$display("-------|--");
		$monitor("%b %b %b %b| %b", A, B, C,D, out);
		A=0; B=0; C=0; D=0;
		#1 D=1; 
		#1 D=0; C=1;
		#1 D=1; 
		#1 D=0; C=0; B=1;
		#1 D=1; 
		#1 D=0; C=1;
		#1 D=1; 
		#1 D=0; C=0; B=0; A=1;
		#1 D=1; 
		#1 D=0; C=1;
		#1 D=1; 
		#1 D=0; C=0; B=1;
		#1 D=1; 
		#1 D=0; C=1;
		#1 D=1; 
		#1 $finish;
	end
	
initial 
	begin 
		$dumpfile("Tabla3POS_tb.vcd");
		$dumpvars(0, Tabla3POS);
	end 
endmodule

Lab 3/Tabla3POS/Tabla3POS_tb.vcd
$date
	Sun Aug 02 14:10:33 2020
$end
$version
	Icarus Verilog
$end
$timescale
	1ps
$end
$scope module Tabla3POS $end
$var wire 1 ! out $end
$var wire 1 " wAn $end
$var wire 1 # wBn $end
$var wire 1 $ wCn $end
$var wire 1 % wDn $end
$var wire 1 & wo1 $end
$var wire 1 ' wo2 $end
$var wire 1 ( wo3 $end
$var wire 1 ) wo4 $end
$var wire 1 * wo5 $end
$var wire 1 + wo6 $end
$var wire 1 , wo7 $end
$var wire 1 - wo8 $end
$var wire 1 . wo9 $end
$var reg 1 / A $end
$var reg 1 0 B $end
$var reg 1 1 C $end
$var reg 1 2 D $end
$upscope $end
$enddefinitions $end
#0
$dumpvars
02
01
00
0/
1.
1-
1,
1+
1*
1)
1(
1'
1&
1%
1$
1#
1"
1!
$end
#1
0%
12
#2
0$
1%
11
02
#3
0%
12
#4
0!
0&
0#
1$
1%
10
01
02
#5
0'
1&
0%
12
#6
0(
1'
0$
1%
11
02
#7
0)
1(
0%
12
#8
1!
1)
0"
1#
1$
1%
1/
00
01
02
#9
0!
0*
0%
12
#10
1!
1*
0$
1%
11
02
#11
0!
0+
0%
12
#12
0,
1+
0#
1$
1%
10
01
02
#13
0-
1,
0%
12
#14
1!
1-
0$
1%
11
02
#15
0!
0.
0%
12
