Lab4/EJERCICIO 04/Laboratorio4.v

//Fredy Godoy - 19260 - Digital1 
//Ejercicios del 1 al 4

//Ejercicio 01 - Tabla 1 - Ecuacion1 Y=A'C'+AB'+AC
module Ecuacion1(input wire A,B,C, output wire out1 );
	wire wAn, wBn, wCn, wa1, wa2, wa3, wa4, wa5; //w=wire "A" "B" "C" n=not a=and 
	
	
	
	not (wAn, A);
	not (wBn, B);
	not (wCn, C);
	and (wa1,wAn,wCn);
	and (wa2,A,wBn);
	and (wa3,A,C);
	or  (out1,wa1,wa2,wa3);
	
endmodule
//--------------------------------------------------------------------------------------------------------------------------
//Ejercicio 01 - Tabla 2 - Ecuacion2 Y=B'
module Ecuacion2(input wire B, output wire out2);
	wire  wBn; //w=wire "A" "B" "C" n=not a=and 
	

	not (out2, B);
	
endmodule
//--------------------------------------------------------------------------------------------------------------------------
//Ejercicio 01 - Tabla 3 - Ecuacion3 Y=A'B'C'D'+ABC'D'+A'BC'D+AB'C'D+A'B'CD+ABCD+A'BCD'+AB'CD'
module Ecuacion3(input wire A,B,C,D, output wire out3);
	wire wAn, wBn, wCn,wDn, wa1, wa2, wa3, wa4, wa5, wa6, wa7, wa8; //w=wire "A" "B" "C" n=not a=and 
		

	not (wAn, A);
	not (wBn, B);
	not (wCn, C);
	not (wDn, D);
	and (wa1,wAn,wBn,wCn,wDn);
	and (wa2,A,B,wCn,wDn);
	and (wa3,wAn,B,wCn,D);
	and (wa4,A,wBn,wCn,D);
	and (wa5,wAn,wBn,C,D);
	and (wa6,A,B,C,D);
	and (wa7,wAn,B,C,wDn);
	and (wa8,A,wBn,C,wDn);
	or  (out3,wa1,wa2,wa3,wa4, wa5, wa6, wa7, wa8);
	
endmodule
//--------------------------------------------------------------------------------------------------------------------------
//Ejercicio 01 - Tabla 4 - Ecuacion4 Y=B'D'+ABD'+BD
module Ecuacion4(input wire A,B,C,D, output wire out4);
	wire wAn, wBn, wCn,wDn, wa1, wa2, wa3,wa4; //w=wire "A" "B" "C" n=not a=and 
	
	

	not (wAn, A);
	not (wBn, B);
	not (wCn, C);
	not (wDn, D);
	and (wa1,wBn,wDn);
	and (wa2,A,B,wDn);
	and (wa3,B,D);
	and (wa4,A,C);
	or  (out4,wa1,wa2,wa3,wa4);
	
endmodule

//--------------------------------------------------------------------------------------------------------------------------
//Ejercicio 02 - Tabla 1 - Ecuacion5 Y=A´B´C´D´+AC´+AB´C+ABCD'
module Ecuacion5(input wire A,B,C,D, output wire out5);
assign out5=(~A&~B&~C&~D)|(A&~C)|(A&~B&C)|(A&B&C&~D);
endmodule
//--------------------------------------------------------------------------------------------------------------------------
//Ejercicio 02 - Tabla 2 - Ecuacion6 Y=C+B'C'
module Ecuacion6(input wire B,C, output wire out6);
assign out6=C|(~B&~C);
endmodule
//--------------------------------------------------------------------------------------------------------------------------
//Ejercicio 02 - Tabla 3 - Ecuacion7 Y=BC'+BC+B'C'D
module Ecuacion7(input wire B,C,D, output wire out7);
assign out7=(B&~C)|(B&C)|(~B&~C&D);
endmodule
//--------------------------------------------------------------------------------------------------------------------------
//Ejercicio 02 - Tabla 4 - Ecuacion8 Y=
module Ecuacion8(input wire A,B,C, output wire out8);
assign out8=B|(~A&~B&~C);
endmodule

Lab4/EJERCICIO 04/Laboratorio4_tb.v

//Fredy Godoy - 19260 - Digital1 
//Ejercicios del 1 al 4

module testbench();
 reg A1,B1,C1,D1,A2,B2,C2,D2;
 wire out1, out2, out3, out4, out5, out6, out7, out8;
 
 Ecuacion1 E1(A1,B1,C1, out1);
 Ecuacion2 E2(B1, out2);
 Ecuacion3 E3(A2,B2,C2,D2, out3);
 Ecuacion4 E4(A2,B2,C2,D2, out4);
 Ecuacion5 E5(A2,B2,C2,D2, out5);
 Ecuacion6 E6(B1,C1, out6);
 Ecuacion7 E7(B2,C2,D2, out7);
 Ecuacion8 E8(A1,B1,C1, out8);
 //----------------------------------------------------------------
 //TABLA 1 Y 2 Ejercicio 01
 initial begin
 $display("Tabla 1 y 2 - Ejercicio 01");
 $display("A B C | Y1 Y2");
 $display("------|------");
 $monitor("%b %b %b | %b %b", A1,B1,C1,out1,out2); 
	A1=0;B1=0;C1=0;
 #1 A1=0;B1=0;C1=1;
 #1 A1=0;B1=1;C1=0; 	
 #1 A1=0;B1=1;C1=1;
 #1 A1=1;B1=0;C1=0;
 #1 A1=1;B1=0;C1=1;
 #1 A1=1;B1=1;C1=0;
 #1 A1=1;B1=1;C1=1;
 end
 //----------------------------------------------------------------
 //TABLA 3 y 4 Ejercicio 01
 initial begin
 #9
 $display("\n");
 $display("Tabla 3 y 4 - Ejercicio 01");
 $display("A B C D | Y1 Y2");
 $display("--------|------");
 $monitor("%b %b %b %b | %b  %b", A2,B2,C2,D2,out3,out4); 
	A2=0;B2=0;C2=0;D2=0;
 #1 A2=0;B2=0;C2=0;D2=1;
 #1 A2=0;B2=0;C2=1;D2=0; 	
 #1 A2=0;B2=0;C2=1;D2=1;
 #1 A2=0;B2=1;C2=0;D2=0;
 #1 A2=0;B2=1;C2=0;D2=1;
 #1 A2=0;B2=1;C2=1;D2=0;
 #1 A2=0;B2=1;C2=1;D2=1;
 #1 A2=1;B2=0;C2=0;D2=0;
 #1 A2=1;B2=0;C2=0;D2=1;
 #1 A2=1;B2=0;C2=1;D2=0; 	
 #1 A2=1;B2=0;C2=1;D2=1;
 #1 A2=1;B2=1;C2=0;D2=0;
 #1 A2=1;B2=1;C2=0;D2=1;
 #1 A2=1;B2=1;C2=1;D2=0;
 #1 A2=1;B2=1;C2=1;D2=1;
 end
 //----------------------------------------------------------------
 //TABLA 1 y 2 Ejercicio 02
 initial begin
 #26
 $display("\n");
 $display("Tabla 1 y 3 - Ejercicio 02");
 $display("A B C D | Y1 Y2");
 $display("--------|------");
 $monitor("%b %b %b %b | %b  %b", A2,B2,C2,D2,out5,out7); 
	A2=0;B2=0;C2=0;D2=0;
 #1 A2=0;B2=0;C2=0;D2=1;
 #1 A2=0;B2=0;C2=1;D2=0; 	
 #1 A2=0;B2=0;C2=1;D2=1;
 #1 A2=0;B2=1;C2=0;D2=0;
 #1 A2=0;B2=1;C2=0;D2=1;
 #1 A2=0;B2=1;C2=1;D2=0;
 #1 A2=0;B2=1;C2=1;D2=1;
 #1 A2=1;B2=0;C2=0;D2=0;
 #1 A2=1;B2=0;C2=0;D2=1;
 #1 A2=1;B2=0;C2=1;D2=0; 	
 #1 A2=1;B2=0;C2=1;D2=1;
 #1 A2=1;B2=1;C2=0;D2=0;
 #1 A2=1;B2=1;C2=0;D2=1;
 #1 A2=1;B2=1;C2=1;D2=0;
 #1 A2=1;B2=1;C2=1;D2=1;
 end

//----------------------------------------------------------------
 //TABLA 2 Y 4 Ejercicio 02
 initial begin
 #42
 $display("\n");
 $display("Tabla 2 y 4 - Ejercicio 02");
 $display("A B C D | Y1 Y2");
 $display("--------|------");
 $monitor("%b %b %b | %b %b", A1,B1,C1,out6,out8); 
	A1=0;B1=0;C1=0;
 #1 A1=0;B1=0;C1=1;
 #1 A1=0;B1=1;C1=0; 	
 #1 A1=0;B1=1;C1=1;
 #1 A1=1;B1=0;C1=0;
 #1 A1=1;B1=0;C1=1;
 #1 A1=1;B1=1;C1=0;
 #1 A1=1;B1=1;C1=1;
 end

 initial 
 #100 $finish;
 
 initial begin 
 $dumpfile("Laboratorio4_tb.vcd");
 $dumpvars(0,testbench);
 end
 
 
 endmodule

Lab4/EJERCICIO 04/Laboratorio4_tb.vcd
$date
	Sat Aug 08 23:19:26 2020
$end
$version
	Icarus Verilog
$end
$timescale
	1ps
$end
$scope module testbench $end
$var wire 1 ! out8 $end
$var wire 1 " out7 $end
$var wire 1 # out6 $end
$var wire 1 $ out5 $end
$var wire 1 % out4 $end
$var wire 1 & out3 $end
$var wire 1 ' out2 $end
$var wire 1 ( out1 $end
$var reg 1 ) A1 $end
$var reg 1 * A2 $end
$var reg 1 + B1 $end
$var reg 1 , B2 $end
$var reg 1 - C1 $end
$var reg 1 . C2 $end
$var reg 1 / D2 $end
$scope module E1 $end
$var wire 1 ) A $end
$var wire 1 + B $end
$var wire 1 - C $end
$var wire 1 ( out1 $end
$var wire 1 0 wAn $end
$var wire 1 1 wBn $end
$var wire 1 2 wCn $end
$var wire 1 3 wa1 $end
$var wire 1 4 wa2 $end
$var wire 1 5 wa3 $end
$upscope $end
$scope module E2 $end
$var wire 1 + B $end
$var wire 1 ' out2 $end
$upscope $end
$scope module E3 $end
$var wire 1 * A $end
$var wire 1 , B $end
$var wire 1 . C $end
$var wire 1 / D $end
$var wire 1 & out3 $end
$var wire 1 6 wAn $end
$var wire 1 7 wBn $end
$var wire 1 8 wCn $end
$var wire 1 9 wDn $end
$var wire 1 : wa1 $end
$var wire 1 ; wa2 $end
$var wire 1 < wa3 $end
$var wire 1 = wa4 $end
$var wire 1 > wa5 $end
$var wire 1 ? wa6 $end
$var wire 1 @ wa7 $end
$var wire 1 A wa8 $end
$upscope $end
$scope module E4 $end
$var wire 1 * A $end
$var wire 1 , B $end
$var wire 1 . C $end
$var wire 1 / D $end
$var wire 1 % out4 $end
$var wire 1 B wAn $end
$var wire 1 C wBn $end
$var wire 1 D wCn $end
$var wire 1 E wDn $end
$var wire 1 F wa1 $end
$var wire 1 G wa2 $end
$var wire 1 H wa3 $end
$var wire 1 I wa4 $end
$upscope $end
$scope module E5 $end
$var wire 1 * A $end
$var wire 1 , B $end
$var wire 1 . C $end
$var wire 1 / D $end
$var wire 1 $ out5 $end
$upscope $end
$scope module E6 $end
$var wire 1 + B $end
$var wire 1 - C $end
$var wire 1 # out6 $end
$upscope $end
$scope module E7 $end
$var wire 1 , B $end
$var wire 1 . C $end
$var wire 1 / D $end
$var wire 1 " out7 $end
$upscope $end
$scope module E8 $end
$var wire 1 ) A $end
$var wire 1 + B $end
$var wire 1 - C $end
$var wire 1 ! out8 $end
$upscope $end
$upscope $end
$enddefinitions $end
#0
$dumpvars
xI
xH
xG
xF
xE
xD
xC
xB
xA
x@
x?
x>
x=
x<
x;
x:
x9
x8
x7
x6
05
04
13
12
11
10
x/
x.
0-
x,
0+
x*
0)
1(
1'
x&
x%
x$
1#
x"
1!
$end
#1
0(
0!
03
02
1-
#2
1(
13
12
0#
01
0'
1!
0-
1+
#3
0(
03
02
1#
1-
#4
1(
14
12
1#
11
1'
0!
00
0-
0+
1)
#5
02
15
1-
#6
0(
04
12
05
0#
01
0'
1!
0-
1+
#7
1(
02
15
1#
1-
#9
1$
1&
1%
0"
1F
1:
19
1E
18
0>
1D
17
0<
0@
1C
0H
16
0;
0=
0?
0A
1B
0G
0I
0/
0.
0,
0*
#10
0$
0&
0%
0:
0F
1"
09
0E
1/
#11
1%
1F
0"
19
1E
08
0D
0/
1.
#12
1&
0%
0F
09
1>
0E
1/
#13
1"
0&
19
1E
18
0>
1D
07
0C
0/
0.
1,
#14
1&
1%
09
1<
0E
1H
1/
#15
1&
1@
0%
19
0<
1E
0H
08
0D
0/
1.
#16
0&
0@
1%
09
0E
1H
1/
#17
1$
0"
1F
1%
19
1E
18
1D
17
1C
0H
06
0B
0/
0.
0,
1*
#18
1&
0%
0F
1"
09
1=
0E
1/
#19
1&
1A
1F
0"
1%
19
0=
1E
08
0D
1I
0/
1.
#20
0&
0A
0F
09
0E
1/
#21
1&
1"
1$
1G
1;
1%
19
1E
18
1D
0I
07
0C
0/
0.
1,
#22
0&
0;
0G
09
0E
1H
1/
#23
1G
19
1E
0H
08
0D
1I
0/
1.
#24
1&
0$
0G
09
1?
0E
1H
1/
#26
1$
0"
1&
1F
1:
1%
19
1E
18
1D
17
1C
0H
16
0?
1B
0I
0/
0.
0,
0*
#27
0$
0&
0%
0:
0F
1"
09
0E
1/
#28
1%
1F
0"
19
1E
08
0D
0/
1.
#29
1&
0%
0F
09
1>
0E
1/
#30
1"
0&
19
1E
18
0>
1D
07
0C
0/
0.
1,
#31
1&
1%
09
1<
0E
1H
1/
#32
1&
1@
0%
19
0<
1E
0H
08
0D
0/
1.
#33
0&
0@
1%
09
0E
1H
1/
#34
1$
0"
1F
1%
19
1E
18
1D
17
1C
0H
06
0B
0/
0.
0,
1*
#35
1&
0%
0F
1"
09
1=
0E
1/
#36
1&
1A
1F
0"
1%
19
0=
1E
08
0D
1I
0/
1.
#37
0&
0A
0F
09
0E
1/
#38
1&
1"
1$
1G
1;
1%
19
1E
18
1D
0I
07
0C
0/
0.
1,
#39
0&
0;
0G
09
0E
1H
1/
#40
1G
19
1E
0H
08
0D
1I
0/
1.
#41
1&
0$
0G
09
1?
0E
1H
1/
#42
13
1(
12
1#
11
1'
1!
10
05
0-
0+
0)
#43
0(
0!
03
02
1-
#44
1(
13
12
0#
01
0'
1!
0-
1+
#45
0(
03
02
1#
1-
#46
1(
14
12
1#
11
1'
0!
00
0-
0+
1)
#47
02
15
1-
#48
0(
04
12
05
0#
01
0'
1!
0-
1+
#49
1(
02
15
1#
1-
