Lab9/Ejercicio_3/Ejercicio_3.v

// Fredy Godoy - 19260
// Ejercicio No.3 - Flip Flop tipo JK

// FF D 1bit 
module FlipFlopD_1Bit(Dato, Clk, Reset, Enable, Q);
input Dato, Clk, Reset, Enable; 
output Q;
reg Q;
always @(posedge Clk, Reset, Enable)

if (Reset) begin 
     Q<=0;
end else if(Enable) begin 
     Q<=Dato;
end 
endmodule 

// FF JK 
module FF_JK(J,K,Enable,Reset,Clk,Q);
input J,K,Enable,Reset, Clk;
output Q;
wire Salida_And_1, Salida_And_2, Salida_or, Salida_not_1, Salida_not_2;

always @(posedge Clk,J,K,Enable,Reset,Q );
not (Salida_not_1, K);
not (Salida_not_2, Q);
and (Salida_And_1, Salida_not_1,Q);
and (Salida_And_2,J,Salida_not_2);
or (Salida_or, Salida_And_1,Salida_And_2);

FlipFlopD_1Bit FFD_1(Salida_or, Clk, Reset, Enable, Q);

endmodule

Lab9/Ejercicio_3/Ejercicio_3_tb.v

// Fredy Godoy - 19260
// Ejercicio No.3 - Flip Flop tipo JK


module testbench();
reg j,k,enable, reset, clk;
wire q;

FF_JK ff_jk(j,k,enable, reset, clk,q);

 initial begin
 $display("Flip Flop tipo JK - Ejercicio No.3");
 $display("J  |  K  |  Q");
 $display("---|-----|----");
 $monitor(" %b    %b    %b ",j,k, q);

   j=0;k=0; enable=1; reset=1;
#5 j=1;k=0; enable=1; reset=0;
#5 j=0;k=1; enable=1; reset=0;
#5 j=1;k=1; enable=1; reset=0;
 end

initial begin
clk=0;
forever #1 clk= ~clk;
end
 initial 
 #100 $finish;
initial begin 
 $dumpfile("Ejercicio_3_tb.vcd");
 $dumpvars(0,testbench);
 end
 endmodule

Lab9/Ejercicio_3/Ejercicio_3_tb.vcd
$date
	Sat Oct 31 10:43:45 2020
$end
$version
	Icarus Verilog
$end
$timescale
	1ps
$end
$scope module testbench $end
$var wire 1 ! q $end
$var reg 1 " clk $end
$var reg 1 # enable $end
$var reg 1 $ j $end
$var reg 1 % k $end
$var reg 1 & reset $end
$scope module ff_jk $end
$var wire 1 " Clk $end
$var wire 1 # Enable $end
$var wire 1 $ J $end
$var wire 1 % K $end
$var wire 1 & Reset $end
$var wire 1 ' Salida_And_1 $end
$var wire 1 ( Salida_And_2 $end
$var wire 1 ) Salida_not_1 $end
$var wire 1 * Salida_not_2 $end
$var wire 1 + Salida_or $end
$var wire 1 ! Q $end
$scope module FFD_1 $end
$var wire 1 " Clk $end
$var wire 1 + Dato $end
$var wire 1 # Enable $end
$var wire 1 & Reset $end
$var reg 1 ! Q $end
$upscope $end
$upscope $end
$upscope $end
$enddefinitions $end
#0
$dumpvars
0+
1*
1)
0(
0'
1&
0%
0$
1#
0"
0!
$end
#1
1"
#2
0"
#3
1"
#4
0"
#5
1+
1(
1"
0&
1$
#6
0"
#7
0(
1'
0*
1!
1"
#8
0"
#9
1"
#10
0+
0'
0)
0"
1%
0$
#11
1*
0!
1"
#12
0"
#13
1"
#14
0"
#15
1+
1(
1"
1$
#16
0"
#17
0+
0(
0*
1!
1"
#18
0"
#19
1+
1(
1*
0!
1"
#20
0"
#21
0+
0(
0*
1!
1"
#22
0"
#23
1+
1(
1*
0!
1"
#24
0"
#25
0+
0(
0*
1!
1"
#26
0"
#27
1+
1(
1*
0!
1"
#28
0"
#29
0+
0(
0*
1!
1"
#30
0"
#31
1+
1(
1*
0!
1"
#32
0"
#33
0+
0(
0*
1!
1"
#34
0"
#35
1+
1(
1*
0!
1"
#36
0"
#37
0+
0(
0*
1!
1"
#38
0"
#39
1+
1(
1*
0!
1"
#40
0"
#41
0+
0(
0*
1!
1"
#42
0"
#43
1+
1(
1*
0!
1"
#44
0"
#45
0+
0(
0*
1!
1"
#46
0"
#47
1+
1(
1*
0!
1"
#48
0"
#49
0+
0(
0*
1!
1"
#50
0"
#51
1+
1(
1*
0!
1"
#52
0"
#53
0+
0(
0*
1!
1"
#54
0"
#55
1+
1(
1*
0!
1"
#56
0"
#57
0+
0(
0*
1!
1"
#58
0"
#59
1+
1(
1*
0!
1"
#60
0"
#61
0+
0(
0*
1!
1"
#62
0"
#63
1+
1(
1*
0!
1"
#64
0"
#65
0+
0(
0*
1!
1"
#66
0"
#67
1+
1(
1*
0!
1"
#68
0"
#69
0+
0(
0*
1!
1"
#70
0"
#71
1+
1(
1*
0!
1"
#72
0"
#73
0+
0(
0*
1!
1"
#74
0"
#75
1+
1(
1*
0!
1"
#76
0"
#77
0+
0(
0*
1!
1"
#78
0"
#79
1+
1(
1*
0!
1"
#80
0"
#81
0+
0(
0*
1!
1"
#82
0"
#83
1+
1(
1*
0!
1"
#84
0"
#85
0+
0(
0*
1!
1"
#86
0"
#87
1+
1(
1*
0!
1"
#88
0"
#89
0+
0(
0*
1!
1"
#90
0"
#91
1+
1(
1*
0!
1"
#92
0"
#93
0+
0(
0*
1!
1"
#94
0"
#95
1+
1(
1*
0!
1"
#96
0"
#97
0+
0(
0*
1!
1"
#98
0"
#99
1+
1(
1*
0!
1"
