Lab 3/Tabla2POS/Tabla2POS.v
module Tabla2POS();
	wire wAn, wBn, wCn, wo1, wo2, wo3, wo4,wo5, out; //w=wire "A" "B" "C" n=not a=and o=or 
	reg A,B,C;
	
	not not1(wAn,A);
	not not2(wBn,B);
	not not3(wCn,C);
	or or1(wo1,A,B,C);
	or or2(wo2,A,wBn,C);
	or or3(wo3,A,wBn,wCn);
	or or4(wo4,wAn,B,C);
	or or5(wo5,wAn,B,wCn);
	and and1(out, wo1, wo2, wo3, wo4,wo5);

	
	initial begin 
		$display("A B C | Y");
		$display("------|--");
		$monitor("%b %b %b | %b", A, B, C, out);
		A=0; B=0; C=0;
		#1 C=1;
		#1 B=1; C=0;
		#1 B=1; C=1;
		#1 A=1; B=0; C=0;
		#1 A=1; B=0; C=1;
		#1 A=1; B=1; C=0;
		#1 A=1; B=1; C=1;
		#1 $finish;
	end
	
initial 
	begin 
		$dumpfile("Tabla2POS_tb.vcd");
		$dumpvars(0, Tabla2POS);
	end 
endmodule

Lab 3/Tabla2POS/Tabla2POS_tb.vcd
$date
	Sun Aug 02 13:52:13 2020
$end
$version
	Icarus Verilog
$end
$timescale
	1ps
$end
$scope module Tabla2POS $end
$var wire 1 ! out $end
$var wire 1 " wAn $end
$var wire 1 # wBn $end
$var wire 1 $ wCn $end
$var wire 1 % wo1 $end
$var wire 1 & wo2 $end
$var wire 1 ' wo3 $end
$var wire 1 ( wo4 $end
$var wire 1 ) wo5 $end
$var reg 1 * A $end
$var reg 1 + B $end
$var reg 1 , C $end
$upscope $end
$enddefinitions $end
#0
$dumpvars
0,
0+
0*
1)
1(
1'
1&
0%
1$
1#
1"
0!
$end
#1
1!
1%
0$
1,
#2
0!
0&
1$
0#
0,
1+
#3
0'
1&
0$
1,
#4
1$
1)
0(
1#
1'
0"
0,
0+
1*
#5
0)
1(
0$
1,
#6
1!
1$
1)
0#
0,
1+
#7
0$
1,
