Lab9/Ejercicio_1/Ejercicio_1.v

// Fredy Godoy - 19260
// Ejercicio No.1 - Flip Flop tipo D
// FLip Flop de 1 bit

module FlipFlopD_1Bit(Dato, Clk, Reset, Enable, Q);
input Dato, Clk, Reset, Enable; 
output Q;
reg Q;
always @(posedge Clk, Reset, Enable)

if (Reset) begin 
     Q<=0;
end else if(Enable) begin 
     Q<=Dato;
end 
endmodule 

// FlipFlopD_2Bit
module FlipFlopD_2Bit(Dato_1, Dato_2, Clk, Reset,Enable, Q_1, Q_2);
input Dato_1, Dato_2, Clk, Reset, Enable; 
output Q_1,Q_2;
wire Q_1,Q_2;
FlipFlopD_1Bit Q1(Dato_1, Clk, Reset, Enable, Q_1);
FlipFlopD_1Bit Q2(Dato_2, Clk, Reset, Enable, Q_2);
endmodule 

// FlipFlopD_4Bit
module FlipFlopD_4Bit(Dato_1, Dato_2, Dato_3, Dato_4, Clk, Reset, Enable, Q_1, Q_2, Q_3, Q_4);
input Dato_1, Dato_2,Dato_3, Dato_4, Clk, Reset, Enable; 
output Q_1,Q_2,Q_3,Q_4;
wire Q_1,Q_2,Q_3,Q_4;
 
FlipFlopD_2Bit Q3(Dato_1,Dato_2, Clk, Reset,Enable, Q_1, Q_2);
FlipFlopD_2Bit Q4(Dato_3,Dato_4, Clk, Reset,Enable, Q_3, Q_4);
endmodule

Lab9/Ejercicio_1/Ejercicio_1_tb.v

// Fredy Godoy - 19260
// Ejercicio No.1 - Flip Flop tipo D

module testbench();
reg Dato_1, Dato_2, Dato_3, Dato_4, Clk, Reset, Enable;
wire Q_1, Q_2, Q_3, Q_4;

 FlipFlopD_4Bit FFD(Dato_1, Dato_2, Dato_3, Dato_4, Clk, Reset, Enable, Q_1, Q_2, Q_3, Q_4);

 initial begin
 $display("Flip Flop tipo D de 4Bits - Ejercicio No.1");
 $display("Dato  |  Q");
 $display("------|----");
 $monitor("%b%b%b%b    | %b%b%b%b", Dato_1, Dato_2, Dato_3, Dato_4, Q_1, Q_2, Q_3, Q_4);

   Dato_1=0; Dato_2=0; Dato_3=0; Dato_4=0; Reset=0; Enable=0;
#2 Dato_1=1; Dato_2=0; Dato_3=0; Dato_4=0; Reset=0; Enable=0;
#2 Dato_1=1; Dato_2=0; Dato_3=1; Dato_4=0; Reset=0; Enable=0;
#2 Dato_1=0; Dato_2=0; Dato_3=1; Dato_4=0; Reset=0; Enable=1;
#2 Dato_1=0; Dato_2=0; Dato_3=0; Dato_4=1; Reset=0; Enable=1;
#2 Dato_1=0; Dato_2=0; Dato_3=0; Dato_4=1; Reset=1; Enable=0;
#2 Dato_1=1; Dato_2=1; Dato_3=0; Dato_4=0; Reset=0; Enable=0;

 end  


initial begin
Clk=0;
forever #1 Clk= ~Clk;
end
 initial 
 #100 $finish;
initial begin 
 $dumpfile("Ejercicio_1_tb.vcd");
 $dumpvars(0,testbench);
 end
 
 
 endmodule

Lab9/Ejercicio_1/Ejercicio_1_tb.vcd
$date
	Sat Oct 31 11:13:56 2020
$end
$version
	Icarus Verilog
$end
$timescale
	1ps
$end
$scope module testbench $end
$var wire 1 ! Q_4 $end
$var wire 1 " Q_3 $end
$var wire 1 # Q_2 $end
$var wire 1 $ Q_1 $end
$var reg 1 % Clk $end
$var reg 1 & Dato_1 $end
$var reg 1 ' Dato_2 $end
$var reg 1 ( Dato_3 $end
$var reg 1 ) Dato_4 $end
$var reg 1 * Enable $end
$var reg 1 + Reset $end
$scope module FFD $end
$var wire 1 % Clk $end
$var wire 1 & Dato_1 $end
$var wire 1 ' Dato_2 $end
$var wire 1 ( Dato_3 $end
$var wire 1 ) Dato_4 $end
$var wire 1 * Enable $end
$var wire 1 + Reset $end
$var wire 1 ! Q_4 $end
$var wire 1 " Q_3 $end
$var wire 1 # Q_2 $end
$var wire 1 $ Q_1 $end
$scope module Q3 $end
$var wire 1 % Clk $end
$var wire 1 & Dato_1 $end
$var wire 1 ' Dato_2 $end
$var wire 1 * Enable $end
$var wire 1 + Reset $end
$var wire 1 # Q_2 $end
$var wire 1 $ Q_1 $end
$scope module Q1 $end
$var wire 1 % Clk $end
$var wire 1 & Dato $end
$var wire 1 * Enable $end
$var wire 1 + Reset $end
$var reg 1 $ Q $end
$upscope $end
$scope module Q2 $end
$var wire 1 % Clk $end
$var wire 1 ' Dato $end
$var wire 1 * Enable $end
$var wire 1 + Reset $end
$var reg 1 # Q $end
$upscope $end
$upscope $end
$scope module Q4 $end
$var wire 1 % Clk $end
$var wire 1 ( Dato_1 $end
$var wire 1 ) Dato_2 $end
$var wire 1 * Enable $end
$var wire 1 + Reset $end
$var wire 1 ! Q_2 $end
$var wire 1 " Q_1 $end
$scope module Q1 $end
$var wire 1 % Clk $end
$var wire 1 ( Dato $end
$var wire 1 * Enable $end
$var wire 1 + Reset $end
$var reg 1 " Q $end
$upscope $end
$scope module Q2 $end
$var wire 1 % Clk $end
$var wire 1 ) Dato $end
$var wire 1 * Enable $end
$var wire 1 + Reset $end
$var reg 1 ! Q $end
$upscope $end
$upscope $end
$upscope $end
$upscope $end
$enddefinitions $end
#0
$dumpvars
0+
0*
0)
0(
0'
0&
0%
x$
x#
x"
x!
$end
#1
1%
#2
0%
1&
#3
1%
#4
0%
1(
#5
1%
#6
0$
0#
1"
0!
0%
1*
0&
#7
1%
#8
0%
1)
0(
#9
0"
1!
1%
#10
0!
0%
0*
1+
#11
1%
#12
0%
0+
0)
1'
1&
