Lab9/Ejercicio_5/Ejercicio_5.v

// Fredy Godoy - 19260
// Ejercicio No.5 - Memoria Rom

module M_Rom(input wire [6:0]Localidad, output reg [12:0]Datos);
//reg [7:0] Memoria[0:128];+

always @(*) begin 
    case(Localidad)
    7'bxxxxxx0: Datos<=13'b1000000001000;
    7'b00001x1: Datos<=13'b0100000001000;
    7'b00000x1: Datos<=13'b1000000001000;
    7'b00011x1: Datos<=13'b1000000001000;
    7'b00010x1: Datos<=13'b0100000001000;
    7'b0010xx1: Datos<=13'b0001001000010;
    7'b0011xx1: Datos<=13'b1001001100000;
    7'b0100xx1: Datos<=13'b0011010000010;
    7'b0101xx1: Datos<=13'b0011010000100;
    7'b0110xx1: Datos<=13'b1011010100000;
    7'b0111xx1: Datos<=13'b1000000111000;
    7'b1000x11: Datos<=13'b0100000001000;
    7'b1000x01: Datos<=13'b1000000001000;
    7'b1001x11: Datos<=13'b1000000001000;
    7'b1001x01: Datos<=13'b0100000001000;
    7'b1010xx1: Datos<=13'b0011011000010;
    7'b1011xx1: Datos<=13'b1011011100000;
    7'b1100xx1: Datos<=13'b0100000001000;
    7'b1101xx1: Datos<=13'b0000000001001;
    7'b1110xx1: Datos<=13'b0011100000010;
    7'b1111xx1: Datos<=13'b1011100100000;

    endcase 
end
endmodule

Lab9/Ejercicio_5/Ejercicio_5_tb.v

// Fredy Godoy - 19260
// Ejercicio No.5 - Memoria Rom
module testbench();

reg [6:0]localidad;
wire [12:0]datos;

M_Rom memoria(localidad,datos);

initial begin
$display("----------Memoria Rom-------");
$display("Localidad       |    Lectura ");
$monitor("    %b    |   %b    ", localidad, datos);
   localidad=7'bxxxxxx0;
#1 localidad=7'b0000000;
#1 localidad=7'b1111110;

   
#1 localidad=7'b00001x1;
#1 localidad=7'b00000x1;
#1 localidad=7'b00011x1;
#1 localidad=7'b00010x1;
#1 localidad=7'b0010xx1;
#1 localidad=7'b0011xx1;

#1 localidad=7'b0100111;
#1 localidad=7'b0100001;
#1 localidad=7'b0100101;

#1 localidad=7'b0101xx1;
#1 localidad=7'b0110xx1;
#1 localidad=7'b0111xx1;
#1 localidad=7'b1000x11;
#1 localidad=7'b1000x01;

#1 localidad=7'b1001011;
#1 localidad=7'b1001111;


#1 localidad=7'b1001x01;
#1 localidad=7'b1010xx1;
#1 localidad=7'b1011xx1;

#1 localidad=7'b1100111;
#1 localidad=7'b1100011;
#1 localidad=7'b1100101;


#1 localidad=7'b1101xx1;
#1 localidad=7'b1110xx1;
#1 localidad=7'b1111xx1;

end 

initial 
#100 $finish;


initial begin 
 $dumpfile("Ejercicio_5_tb.vcd");
 $dumpvars(0,testbench);
end
endmodule

Lab9/Ejercicio_5/Ejercicio_5_tb.vcd
$date
	Sat Oct 31 10:47:31 2020
$end
$version
	Icarus Verilog
$end
$timescale
	1ps
$end
$scope module testbench $end
$var wire 13 ! datos [12:0] $end
$var reg 7 " localidad [6:0] $end
$scope module memoria $end
$var wire 7 # Localidad [6:0] $end
$var reg 13 $ Datos [12:0] $end
$upscope $end
$upscope $end
$enddefinitions $end
#0
$dumpvars
b1000000001000 $
bx0 #
bx0 "
b1000000001000 !
$end
#1
b0 "
b0 #
#2
b1111110 "
b1111110 #
#3
b100000001000 !
b100000001000 $
b1x1 "
b1x1 #
#4
b1000000001000 !
b1000000001000 $
b0x1 "
b0x1 #
#5
b11x1 "
b11x1 #
#6
b100000001000 !
b100000001000 $
b10x1 "
b10x1 #
#7
b1001000010 !
b1001000010 $
b10xx1 "
b10xx1 #
#8
b1001001100000 !
b1001001100000 $
b11xx1 "
b11xx1 #
#9
b100111 "
b100111 #
#10
b100001 "
b100001 #
#11
b100101 "
b100101 #
#12
b11010000100 !
b11010000100 $
b101xx1 "
b101xx1 #
#13
b1011010100000 !
b1011010100000 $
b110xx1 "
b110xx1 #
#14
b1000000111000 !
b1000000111000 $
b111xx1 "
b111xx1 #
#15
b100000001000 !
b100000001000 $
b1000x11 "
b1000x11 #
#16
b1000000001000 !
b1000000001000 $
b1000x01 "
b1000x01 #
#17
b1001011 "
b1001011 #
#18
b1001111 "
b1001111 #
#19
b100000001000 !
b100000001000 $
b1001x01 "
b1001x01 #
#20
b11011000010 !
b11011000010 $
b1010xx1 "
b1010xx1 #
#21
b1011011100000 !
b1011011100000 $
b1011xx1 "
b1011xx1 #
#22
b1100111 "
b1100111 #
#23
b1100011 "
b1100011 #
#24
b1100101 "
b1100101 #
#25
b1001 !
b1001 $
b1101xx1 "
b1101xx1 #
#26
b11100000010 !
b11100000010 $
b1110xx1 "
b1110xx1 #
#27
b1011100100000 !
b1011100100000 $
b1111xx1 "
b1111xx1 #
