Lab 3/Tabla1POS/Tabla1POS.v
module Tabla1POS();
	wire wAn, wBn, wCn, wo1, wo2, wo3, out; //w=wire "A" "B" "C" n=not a=and 
	reg A,B,C;
	
	not not1(wAn,A);
	not not2(wBn,B);
	not not3(wCn,C);
	or or1(wo1,A,B,wCn);
	or or2(wo2,A,wBn,wCn);
	or or3(wo3,wAn,wBn,C);
	and and1(out, wo1,wo2,wo3);

	
	initial begin 
		$display("A B C | Y");
		$display("------|--");
		$monitor("%b %b %b | %b", A, B, C, out);
		A=0; B=0; C=0;
		#1 C=1;
		#1 B=1; C=0;
		#1 B=1; C=1;
		#1 A=1; B=0; C=0;
		#1 A=1; B=0; C=1;
		#1 A=1; B=1; C=0;
		#1 A=1; B=1; C=1;
		#1 $finish;
	end
	
initial 
	begin 
		$dumpfile("Tabla1POS_tb.vcd");
		$dumpvars(0, Tabla1POS);
	end 
endmodule

Lab 3/Tabla1POS/Tabla1POS.vcd
$date
	Fri Jul 31 23:05:37 2020
$end
$version
	Icarus Verilog
$end
$timescale
	1ps
$end
$scope module Tabla1POS $end
$var wire 1 ! out $end
$var wire 1 " wAn $end
$var wire 1 # wBn $end
$var wire 1 $ wCn $end
$var wire 1 % wo1 $end
$var wire 1 & wo2 $end
$var wire 1 ' wo3 $end
$var reg 1 ( A $end
$var reg 1 ) B $end
$var reg 1 * C $end
$upscope $end
$enddefinitions $end
#0
$dumpvars
0*
0)
0(
1'
1&
1%
1$
1#
1"
1!
$end
#1
0!
0%
0$
1*
#2
1!
1$
1%
0#
0*
1)
#3
0!
0&
0$
1*
#4
1!
1$
1#
1&
0"
0*
0)
1(
#5
0$
1*
#6
0!
0'
1$
0#
0*
1)
#7
1!
1'
0$
1*
