Lab10/Ejercicio_1/Ejercicio_1.v
// Fredy Godoy - 19260
// Ejercicio No.1 -  Conjunto de Program Counter, Rom, Fetch

module Program_Counter(Enable_PCounter, Load_PCounter,Clk, 
Reset,Activacion_PCounter_Load,Salida_PCounter);

input Enable_PCounter,Activacion_PCounter_Load,Clk, Reset;
input [11:0]Load_PCounter;
output [11:0]Salida_PCounter;
reg [11:0]Salida_PCounter;
always @(posedge Clk,Activacion_PCounter_Load,Reset, posedge Enable_PCounter)
if(Reset) 
Salida_PCounter <= 12'b0; //000000000000

else if (Activacion_PCounter_Load)
Salida_PCounter <= Load_PCounter;

else if (Enable_PCounter) 
Salida_PCounter <= Salida_PCounter + 1;

endmodule


module M_Rom(input wire [11:0]Localidad, output wire [7:0]Datos_Rom);
reg [7:0] Memoria[0:4096];
initial begin
$readmemb("Datos_Mem_Rom.F", Memoria);
end 
assign Datos_Rom =  Memoria[Localidad];
endmodule
 

module Fetch_8Bits(Salida_Rom, Clk, Reset, Enable_Fetch, Instr, Oprnd);
input [7:0]Salida_Rom;
input Clk, Reset, Enable_Fetch; 
output reg [3:0]Instr, Oprnd;

always @(posedge Clk, Reset, Enable_Fetch)

if (Reset) begin
     {Instr, Oprnd}<=8'b0; 
     
end else if(Enable_Fetch) begin 
     {Instr, Oprnd}<=Salida_Rom;
end 
endmodule 


// Union de los modulos 
module PC_ROM_Fetch(
//Entradas comunes
Reset, Clk, 
//Entradas de Program counter
Load_PCounter, Enable_PCounter,Activacion_PCounter_Load,
// Entradas de Fetch
Enable_Fetch, Instr, Oprnd 
 );

input Reset, Clk;
input [11:0]Load_PCounter;
wire [11:0]Salida_PCounter;
//output [11:0]Salida_PCounter;
wire [7:0]Datos_Rom;
input Enable_PCounter,Activacion_PCounter_Load, Enable_Fetch;
output [3:0]Instr, Oprnd;


Program_Counter PC(Enable_PCounter, Load_PCounter,Clk, 
Reset,Activacion_PCounter_Load,Salida_PCounter);

M_Rom rom(Salida_PCounter, Datos_Rom);

Fetch_8Bits Fetch (Datos_Rom, Clk, Reset, Enable_Fetch, Instr, Oprnd);

endmodule

Lab10/Ejercicio_1/Ejercicio_1_tb.v
// Fredy Godoy - 19260
// Ejercicio No.1 - Flip Flop tipo D

module testbench();

reg Reset, Clk;
reg [11:0]Load_PCounter;
reg Enable_PCounter,Activacion_PCounter_Load, Enable_Fetch;
wire [3:0]Instr, Oprnd;


PC_ROM_Fetch modulo_1(
Reset, Clk, 
//Entradas de Program counter
Load_PCounter, Enable_PCounter,Activacion_PCounter_Load,
// Entradas de Fetch
Enable_Fetch, Instr, Oprnd 
);

 initial begin
 $display("Prueba fetch");
 $display(" Instr Oprnd ");
 $display("--------------");
 $monitor(" %b   %b", Instr, Oprnd);

Reset=1;  
   Enable_PCounter=1; Activacion_PCounter_Load=0; Enable_Fetch=1; 
#1 Reset=0;  
   Enable_PCounter=1; Activacion_PCounter_Load=0; Enable_Fetch=1; 

 end  


initial begin
Clk=0;
forever #1 Clk= ~Clk;
end
 initial 
 #100 $finish;
initial begin 
 $dumpfile("Ejercicio_1_tb.vcd");
 $dumpvars(0,testbench);
 end
 
 
 endmodule

Lab10/Ejercicio_1/Ejercicio_1_tb.vcd
$date
	Sat Nov 07 23:38:01 2020
$end
$version
	Icarus Verilog
$end
$timescale
	1ps
$end
$scope module testbench $end
$var wire 4 ! Oprnd [3:0] $end
$var wire 4 " Instr [3:0] $end
$var reg 1 # Activacion_PCounter_Load $end
$var reg 1 $ Clk $end
$var reg 1 % Enable_Fetch $end
$var reg 1 & Enable_PCounter $end
$var reg 12 ' Load_PCounter [11:0] $end
$var reg 1 ( Reset $end
$scope module modulo_1 $end
$var wire 1 # Activacion_PCounter_Load $end
$var wire 1 $ Clk $end
$var wire 1 % Enable_Fetch $end
$var wire 1 & Enable_PCounter $end
$var wire 12 ) Load_PCounter [11:0] $end
$var wire 1 ( Reset $end
$var wire 12 * Salida_PCounter [11:0] $end
$var wire 4 + Oprnd [3:0] $end
$var wire 4 , Instr [3:0] $end
$var wire 8 - Datos_Rom [7:0] $end
$scope module Fetch $end
$var wire 1 $ Clk $end
$var wire 1 % Enable_Fetch $end
$var wire 1 ( Reset $end
$var wire 8 . Salida_Rom [7:0] $end
$var reg 4 / Instr [3:0] $end
$var reg 4 0 Oprnd [3:0] $end
$upscope $end
$scope module PC $end
$var wire 1 # Activacion_PCounter_Load $end
$var wire 1 $ Clk $end
$var wire 1 & Enable_PCounter $end
$var wire 12 1 Load_PCounter [11:0] $end
$var wire 1 ( Reset $end
$var reg 12 2 Salida_PCounter [11:0] $end
$upscope $end
$scope module rom $end
$var wire 8 3 Datos_Rom [7:0] $end
$var wire 12 4 Localidad [11:0] $end
$upscope $end
$upscope $end
$upscope $end
$enddefinitions $end
#0
$dumpvars
b0 4
b1111 3
b0 2
bx 1
b0 0
b0 /
b1111 .
b1111 -
b0 ,
b0 +
b0 *
bx )
1(
bx '
1&
1%
0$
0#
b0 "
b0 !
$end
#1
b1111 !
b1111 +
b1111 0
b11110000 -
b11110000 .
b11110000 3
b1 *
b1 2
b1 4
1$
0(
#2
0$
#3
b1111 "
b1111 ,
b1111 /
b0 !
b0 +
b0 0
bx -
bx .
bx 3
b10 *
b10 2
b10 4
1$
#4
0$
#5
bx "
bx ,
bx /
bx !
bx +
bx 0
b11 *
b11 2
b11 4
1$
#6
0$
#7
b100 *
b100 2
b100 4
1$
#8
0$
#9
b10101010 -
b10101010 .
b10101010 3
b101 *
b101 2
b101 4
1$
#10
0$
#11
b1010 "
b1010 ,
b1010 /
b1010 !
b1010 +
b1010 0
b1010101 -
b1010101 .
b1010101 3
b110 *
b110 2
b110 4
1$
#12
0$
#13
b101 "
b101 ,
b101 /
b101 !
b101 +
b101 0
b11001100 -
b11001100 .
b11001100 3
b111 *
b111 2
b111 4
1$
#14
0$
#15
b1100 "
b1100 ,
b1100 /
b1100 !
b1100 +
b1100 0
b110011 -
b110011 .
b110011 3
b1000 *
b1000 2
b1000 4
1$
#16
0$
#17
b11 "
b11 ,
b11 /
b11 !
b11 +
b11 0
b10011001 -
b10011001 .
b10011001 3
b1001 *
b1001 2
b1001 4
1$
#18
0$
#19
b1001 "
b1001 ,
b1001 /
b1001 !
b1001 +
b1001 0
b1100110 -
b1100110 .
b1100110 3
b1010 *
b1010 2
b1010 4
1$
#20
0$
#21
b110 "
b110 ,
b110 /
b110 !
b110 +
b110 0
b11111111 -
b11111111 .
b11111111 3
b1011 *
b1011 2
b1011 4
1$
#22
0$
#23
b1111 "
b1111 ,
b1111 /
b1111 !
b1111 +
b1111 0
b0 -
b0 .
b0 3
b1100 *
b1100 2
b1100 4
1$
#24
0$
#25
b0 "
b0 ,
b0 /
b0 !
b0 +
b0 0
bx -
bx .
bx 3
b1101 *
b1101 2
b1101 4
1$
#26
0$
#27
bx "
bx ,
bx /
bx !
bx +
bx 0
b1110 *
b1110 2
b1110 4
1$
#28
0$
#29
b1111 *
b1111 2
b1111 4
1$
#30
0$
#31
b10000 *
b10000 2
b10000 4
1$
#32
0$
#33
b10001 *
b10001 2
b10001 4
1$
#34
0$
#35
b10010 *
b10010 2
b10010 4
1$
#36
0$
#37
b10011 *
b10011 2
b10011 4
1$
#38
0$
#39
b10100 *
b10100 2
b10100 4
1$
#40
0$
#41
b10101 *
b10101 2
b10101 4
1$
#42
0$
#43
b10110 *
b10110 2
b10110 4
1$
#44
0$
#45
b10111 *
b10111 2
b10111 4
1$
#46
0$
#47
b11000 *
b11000 2
b11000 4
1$
#48
0$
#49
b11001 *
b11001 2
b11001 4
1$
#50
0$
#51
b11010 *
b11010 2
b11010 4
1$
#52
0$
#53
b11011 *
b11011 2
b11011 4
1$
#54
0$
#55
b11100 *
b11100 2
b11100 4
1$
#56
0$
#57
b11101 *
b11101 2
b11101 4
1$
#58
0$
#59
b11110 *
b11110 2
b11110 4
1$
#60
0$
#61
b11111 *
b11111 2
b11111 4
1$
#62
0$
#63
b100000 *
b100000 2
b100000 4
1$
#64
0$
#65
b100001 *
b100001 2
b100001 4
1$
#66
0$
#67
b100010 *
b100010 2
b100010 4
1$
#68
0$
#69
b100011 *
b100011 2
b100011 4
1$
#70
0$
#71
b100100 *
b100100 2
b100100 4
1$
#72
0$
#73
b100101 *
b100101 2
b100101 4
1$
#74
0$
#75
b100110 *
b100110 2
b100110 4
1$
#76
0$
#77
b100111 *
b100111 2
b100111 4
1$
#78
0$
#79
b101000 *
b101000 2
b101000 4
1$
#80
0$
#81
b101001 *
b101001 2
b101001 4
1$
#82
0$
#83
b101010 *
b101010 2
b101010 4
1$
#84
0$
#85
b101011 *
b101011 2
b101011 4
1$
#86
0$
#87
b101100 *
b101100 2
b101100 4
1$
#88
0$
#89
b101101 *
b101101 2
b101101 4
1$
#90
0$
#91
b101110 *
b101110 2
b101110 4
1$
#92
0$
#93
b101111 *
b101111 2
b101111 4
1$
#94
0$
#95
b110000 *
b110000 2
b110000 4
1$
#96
0$
#97
b110001 *
b110001 2
b110001 4
1$
#98
0$
#99
b110010 *
b110010 2
b110010 4
1$
