Lab 3/Tabla2SOP/Tabla2SOP.v
module Tabla2SOP();
	wire wAn, wBn, wCn, wa1, wa2, wa3, out; //w=wire "A" "B" "C" n=not a=and o=or
	reg A,B,C;
	
	not not1(wAn,A);
	not not2(wBn,B);
	not not3(wCn,C);
	and and1(wa1,wAn,wBn,C);
	and and2(wa2,A,B,wCn);
	and and3(wa3,A,B,C);
	or or1(out, wa1,wa2, wa3);

	
	initial begin 
		$display("A B C | Y");
		$display("------|--");
		$monitor("%b %b %b | %b", A, B, C, out);
		A=0; B=0; C=0;
		#1 C=1;
		#1 B=1; C=0;
		#1 B=1; C=1;
		#1 A=1; B=0; C=0;
		#1 A=1; B=0; C=1;
		#1 A=1; B=1; C=0;
		#1 A=1; B=1; C=1;
		#1 $finish;
	end
	
initial 
	begin 
		$dumpfile("Tabla2SOP_tb.vcd");
		$dumpvars(0, Tabla2SOP);
	end 
endmodule

Lab 3/Tabla2SOP/Tabla2SOP_tb.vcd
$date
	Sun Aug 02 14:01:30 2020
$end
$version
	Icarus Verilog
$end
$timescale
	1ps
$end
$scope module Tabla2SOP $end
$var wire 1 ! out $end
$var wire 1 " wAn $end
$var wire 1 # wBn $end
$var wire 1 $ wCn $end
$var wire 1 % wa1 $end
$var wire 1 & wa2 $end
$var wire 1 ' wa3 $end
$var reg 1 ( A $end
$var reg 1 ) B $end
$var reg 1 * C $end
$upscope $end
$enddefinitions $end
#0
$dumpvars
0*
0)
0(
0'
0&
0%
1$
1#
1"
0!
$end
#1
1!
1%
0$
1*
#2
0!
0%
1$
0#
0*
1)
#3
0$
1*
#4
1$
1#
0"
0*
0)
1(
#5
0$
1*
#6
1!
1&
1$
0#
0*
1)
#7
0&
1'
0$
1*
