Lab 3/Tabla1SOP/Tabla1SOP.v
module Tabla1SOP ();
	wire wAn, wBn, wCn, wa1, wa2, wa3, wa4, wa5, out; //w=wire "A" "B" "C" n=not a=and 
	reg A,B,C;
	
	
	not not1(wAn, A);
	not not2(wBn, B);
	not not3(wCn, C);
	and and1(wa1,wAn,wBn,wCn);
	and and2(wa2,wAn,B,wCn);
	and and3(wa3,A,wBn,wCn);
	and and4(wa4,A,wBn,C);
	and and5(wa5,A,B,C);
	or or1(out,wa1,wa2,wa3,wa4,wa5);
	
	initial begin 
		$display("A B C | Y");
		$display("------|--");
		$monitor("%b %b %b | %b", A, B, C, out);
		A=0; B=0; C=0;
		#1 C=1;
		#1 B=1; C=0;
		#1 B=1; C=1;
		#1 A=1; B=0; C=0;
		#1 A=1; B=0; C=1;
		#1 A=1; B=1; C=0;
		#1 A=1; B=1; C=1;
		#1 $finish;
	end
	
initial 
	begin 
		$dumpfile("Tabla1SOP_tb.vcd");
		$dumpvars(0, Tabla1SOP);
	end 
endmodule

Lab 3/Tabla1SOP/Tabla1SOP_tb.vcd
$date
	Sun Aug 02 13:32:41 2020
$end
$version
	Icarus Verilog
$end
$timescale
	1ps
$end
$scope module Tabla1SOP $end
$var wire 1 ! out $end
$var wire 1 " wAn $end
$var wire 1 # wBn $end
$var wire 1 $ wCn $end
$var wire 1 % wa1 $end
$var wire 1 & wa2 $end
$var wire 1 ' wa3 $end
$var wire 1 ( wa4 $end
$var wire 1 ) wa5 $end
$var reg 1 * A $end
$var reg 1 + B $end
$var reg 1 , C $end
$upscope $end
$enddefinitions $end
#0
$dumpvars
0,
0+
0*
0)
0(
0'
0&
1%
1$
1#
1"
1!
$end
#1
0!
0%
0$
1,
#2
1!
1&
1$
0#
0,
1+
#3
0!
0&
0$
1,
#4
1!
1'
1$
1#
0"
0,
0+
1*
#5
0'
1(
0$
1,
#6
0!
0(
1$
0#
0,
1+
#7
1!
1)
0$
1,
