Lab10/Ejercicio_2/Ejercicio_2.v

// Fredy Godoy - 19260
// Ejercicio No.2 -  Conjunto de Acumulador, Bus driver y Alu

//modulo de bus driver 
module Bus_Driver(Entrada, Enable, Salida);
input [3:0]Entrada; 
input Enable;
output [3:0]Salida; 
reg [3:0]Salida;

always @(*) 
if (Enable) begin
    Salida<=Entrada;
end else begin
    Salida<=4'bzzzz;
end
endmodule 

// Modulo de acumulador
module Acumulador(Dato, Clk, Reset, Enable, Salida);
input [3:0]Dato;
input Clk, Reset, Enable; 
output [3:0]Salida;
reg [3:0]Salida;
always @(posedge Clk, Reset, Enable)

if (Reset) begin 
     Salida<=0;
end else if(Enable) begin 
     Salida<=Dato;
end 
endmodule 

// Modulo de la Alu 
module ALU(input logic [2:0]Seleccion,input [3:0]A,B,output [4:0]Output, output reg Zero);
reg[4:0]Output;
always @(*) begin
case(Seleccion)
3'b000:  Output <= ~(A & B);
3'b001:  Output <= A;
3'b010:  Output <= B;
3'b011:  Output <= A + B;
3'b100:  Output <= A - B;

default: Output = 4'bxxxx;
endcase
if (Output) 
     assign Zero=0;
 else 
    assign Zero=1;
end

endmodule

// Implementación de todos los modulos
module Acumulador_BusDriver_Alu(Clk, Reset,Seleccion_alu,Entrada_Bus1, Enable_Bus1,Enable_Bus2, Salida_Bus2,Carry,Zero, B,A);
input [3:0]Entrada_Bus1;
input [2:0] Seleccion_alu;
input Clk, Reset,Enable_Bus1,Enable_Bus2, Enable_Acumulador;
output  [3:0]Salida_Bus2;
wire [3:0]Salida_Alu;
output wire[3:0]B,A;
output Carry,Zero;
wire Carry;



Bus_Driver Bus1(Entrada_Bus1, Enable_Bus1, B);
Acumulador Acu(Salida_Alu, Clk, Reset, Enable, A);
ALU alu(Seleccion_alu,A,B,{Carry,Salida_Alu},Zero);
Bus_Driver Bus2(Salida_Alu, Enable_Bus2,Salida_Bus2);


 
endmodule

Lab10/Ejercicio_2/Ejercicio_2_tb.v

// Fredy Godoy - 19260
// Ejercicio No.2 -  Conjunto de Acumulador, Bus driver y Alu

module testbench();
reg Clk, Reset,Enable_Bus1,Enable_Bus2;
reg [2:0]Seleccion_alu;
reg [3:0]Entrada_Bus1; 
wire [3:0]Salida_Bus2;
wire Carry,Zero;
wire [3:0]B,A;

Acumulador_BusDriver_Alu modulo1(Clk, Reset,Seleccion_alu,Entrada_Bus1, Enable_Bus1,Enable_Bus2, Salida_Bus2,Carry,Zero,B,A);

initial begin
$display("-----------------------------------------------------------");
$display("Seleccion alu |   A  |   B  | Carry | Zero | Salida bus 2 ");
$monitor("   %b           | %b | %b |   %b   |   %b   | %b |  ", Seleccion_alu,A,B ,Carry, Zero,Salida_Bus2);
Reset=1;
#1 Reset=0;Seleccion_alu=4'b100;Entrada_Bus1=4'b0; Enable_Bus1=1;Enable_Bus2=1;
#1 Reset=0;Seleccion_alu=4'b100;Entrada_Bus1=4'b1000; Enable_Bus1=1;Enable_Bus2=1;
#1 Reset=0;Seleccion_alu=4'b0;Entrada_Bus1=4'b0; Enable_Bus1=1;Enable_Bus2=1;
#1 Reset=0;Seleccion_alu=4'b1;Entrada_Bus1=4'b1100; Enable_Bus1=1;Enable_Bus2=1;
#1 Reset=0;Seleccion_alu=4'b10;Entrada_Bus1=4'b1010; Enable_Bus1=1;Enable_Bus2=1;
#1 Reset=0;Seleccion_alu=4'b11;Entrada_Bus1=4'b1111; Enable_Bus1=1;Enable_Bus2=1;
#1 Reset=0;Seleccion_alu=4'b100;Entrada_Bus1=4'b1000; Enable_Bus1=1;Enable_Bus2=1;

end 
initial begin
Clk=0;
forever #1 Clk= ~Clk;
end
initial 
#100 $finish;


initial begin 
 $dumpfile("Ejercicio_2_tb.vcd");
 $dumpvars(0,testbench);
end
endmodule

Lab10/Ejercicio_2/Ejercicio_2_tb.vcd
$date
	Sat Nov 07 23:45:44 2020
$end
$version
	Icarus Verilog
$end
$timescale
	1ps
$end
$scope module testbench $end
$var wire 1 ! Zero $end
$var wire 4 " Salida_Bus2 [3:0] $end
$var wire 1 # Carry $end
$var wire 4 $ B [3:0] $end
$var wire 4 % A [3:0] $end
$var reg 1 & Clk $end
$var reg 1 ' Enable_Bus1 $end
$var reg 1 ( Enable_Bus2 $end
$var reg 4 ) Entrada_Bus1 [3:0] $end
$var reg 1 * Reset $end
$var reg 3 + Seleccion_alu [2:0] $end
$scope module modulo1 $end
$var wire 1 & Clk $end
$var wire 1 , Enable $end
$var wire 1 - Enable_Acumulador $end
$var wire 1 ' Enable_Bus1 $end
$var wire 1 ( Enable_Bus2 $end
$var wire 4 . Entrada_Bus1 [3:0] $end
$var wire 1 * Reset $end
$var wire 3 / Seleccion_alu [2:0] $end
$var wire 1 ! Zero $end
$var wire 4 0 Salida_Bus2 [3:0] $end
$var wire 4 1 Salida_Alu [3:0] $end
$var wire 1 # Carry $end
$var wire 4 2 B [3:0] $end
$var wire 4 3 A [3:0] $end
$scope module Acu $end
$var wire 1 & Clk $end
$var wire 4 4 Dato [3:0] $end
$var wire 1 , Enable $end
$var wire 1 * Reset $end
$var reg 4 5 Salida [3:0] $end
$upscope $end
$scope module Bus1 $end
$var wire 1 ' Enable $end
$var wire 4 6 Entrada [3:0] $end
$var reg 4 7 Salida [3:0] $end
$upscope $end
$scope module Bus2 $end
$var wire 1 ( Enable $end
$var wire 4 8 Entrada [3:0] $end
$var reg 4 9 Salida [3:0] $end
$upscope $end
$scope module alu $end
$var wire 4 : A [3:0] $end
$var wire 4 ; B [3:0] $end
$var wire 3 < Seleccion [2:0] $end
$var reg 5 = Output [4:0] $end
$var reg 1 ! Zero $end
$upscope $end
$upscope $end
$upscope $end
$enddefinitions $end
#0
$dumpvars
b0xxxx =
bx <
bx ;
b0 :
bx 9
bx 8
bx 7
bx 6
b0 5
bx 4
b0 3
bx 2
bx 1
bx 0
bx /
bx .
z-
z,
bx +
1*
bx )
x(
x'
0&
b0 %
bx $
0#
bx "
1!
$end
#1
b0 "
b0 0
b0 9
b0 1
b0 4
b0 8
0#
b0 $
b0 2
b0 7
b0 ;
b0 =
1&
1(
1'
b0 )
b0 .
b0 6
b100 +
b100 /
b100 <
0*
#2
b1000 "
b1000 0
b1000 9
0!
b1000 1
b1000 4
b1000 8
1#
b11000 =
b1000 $
b1000 2
b1000 7
b1000 ;
0&
b1000 )
b1000 .
b1000 6
#3
b1111 "
b1111 0
b1111 9
b1111 1
b1111 4
b1111 8
b0 $
b0 2
b0 7
b0 ;
b11111 =
1&
b0 )
b0 .
b0 6
b0 +
b0 /
b0 <
#4
b0 "
b0 0
b0 9
1!
b0 1
b0 4
b0 8
0#
b1100 $
b1100 2
b1100 7
b1100 ;
b0 =
0&
b1100 )
b1100 .
b1100 6
b1 +
b1 /
b1 <
#5
b1010 "
b1010 0
b1010 9
0!
b1010 1
b1010 4
b1010 8
b1010 $
b1010 2
b1010 7
b1010 ;
b1010 =
1&
b1010 )
b1010 .
b1010 6
b10 +
b10 /
b10 <
#6
b1111 "
b1111 0
b1111 9
b1111 1
b1111 4
b1111 8
b1111 =
b1111 $
b1111 2
b1111 7
b1111 ;
0&
b1111 )
b1111 .
b1111 6
b11 +
b11 /
b11 <
#7
b1000 "
b1000 0
b1000 9
b1000 1
b1000 4
b1000 8
1#
b1000 $
b1000 2
b1000 7
b1000 ;
b11000 =
1&
b1000 )
b1000 .
b1000 6
b100 +
b100 /
b100 <
