Lab 3/Tabla3SOP/Tabla3SOP.v
module Tabla3SOP();
	wire wAn, wBn, wCn, wDn, wa1, wa2, wa3, wa4,wa5,wa6,wa7, out; //w=wire "A" "B" "C" "D" n=not a=and o=or 
	reg A,B,C,D;
	
	not not1(wAn,A);
	not not2(wBn,B);
	not not3(wCn,C);
	not not4(wDn,D);
	and and1(wa1, wAn, wBn, wCn, wDn);
	and and2(wa2, wAn, wBn, wCn, D);
	and and3(wa3, wAn, wBn, C, wDn);
	and and4(wa4, wAn, wBn, C, D);
	and and5(wa5, A, wBn, wCn, wDn);
	and and6(wa6, A, wBn, C, wDn);
	and and7(wa7, A, B, C, wDn);
	or or1(out,wa1, wa2, wa3, wa4,wa5,wa6,wa7);
	

	
	initial begin 
		$display("A B C D| Y");
		$display("-------|--");
		$monitor("%b %b %b %b| %b", A, B, C,D, out);
		A=0; B=0; C=0; D=0;
		#1 D=1; 
		#1 D=0; C=1;
		#1 D=1; 
		#1 D=0; C=0; B=1;
		#1 D=1; 
		#1 D=0; C=1;
		#1 D=1; 
		#1 D=0; C=0; B=0; A=1;
		#1 D=1; 
		#1 D=0; C=1;
		#1 D=1; 
		#1 D=0; C=0; B=1;
		#1 D=1; 
		#1 D=0; C=1;
		#1 D=1; 
		#1 $finish;
	end
	
initial 
	begin 
		$dumpfile("Tabla3SOP_tb.vcd");
		$dumpvars(0, Tabla3SOP);
	end 
endmodule

Lab 3/Tabla3SOP/Tabla3SOP_tb.vcd
$date
	Sun Aug 02 14:15:11 2020
$end
$version
	Icarus Verilog
$end
$timescale
	1ps
$end
$scope module Tabla3SOP $end
$var wire 1 ! out $end
$var wire 1 " wAn $end
$var wire 1 # wBn $end
$var wire 1 $ wCn $end
$var wire 1 % wDn $end
$var wire 1 & wa1 $end
$var wire 1 ' wa2 $end
$var wire 1 ( wa3 $end
$var wire 1 ) wa4 $end
$var wire 1 * wa5 $end
$var wire 1 + wa6 $end
$var wire 1 , wa7 $end
$var reg 1 - A $end
$var reg 1 . B $end
$var reg 1 / C $end
$var reg 1 0 D $end
$upscope $end
$enddefinitions $end
#0
$dumpvars
00
0/
0.
0-
0,
0+
0*
0)
0(
0'
1&
1%
1$
1#
1"
1!
$end
#1
0&
1'
0%
10
#2
1(
0$
0'
1%
1/
00
#3
0(
1)
0%
10
#4
0!
0#
1$
0)
1%
1.
0/
00
#5
0%
10
#6
0$
1%
1/
00
#7
0%
10
#8
1!
1*
0"
1#
1$
1%
1-
0.
0/
00
#9
0!
0*
0%
10
#10
1!
1+
0$
1%
1/
00
#11
0!
0+
0%
10
#12
0#
1$
1%
1.
0/
00
#13
0%
10
#14
1!
1,
0$
1%
1/
00
#15
0!
0,
0%
10
