Lab4/EJERCICIO 05/Ejercicio05.v

//--------------------------------------------------------------------------------------------------------------------------
//Ecuacion simplificada 
module simplificada(input wire A,B,C, output wire out1 );
	wire wBn, wa1, wa2, wa3, wa4, wa5; //w=wire "A" "B" "C" n=not a=and 
	
	not (wBn, B);
	and (wa1,A,wBn);
	and (wa2,A,C);
	or  (out1,wa1,wa2);
	
endmodule
//--------------------------------------------------------------------------------------------------------------------------
//Ecuacion SOP
module SOP(input wire A,B,C, output wire out2);
assign out2=(A&~B&~C)|(A&~B&C)|(A&B&C);
endmodule
//--------------------------------------------------------------------------------------------------------------------------
//Ecuacion POS
module POS(input wire A,B,C, output wire out3);
assign out3=(A|B|C)&(A|B|~C)&(A|~B|C)&(A|~B|~C)&(~A|~B|C);
endmodule

Lab4/EJERCICIO 05/Ejercicio05_tb.v
//Fredy Godoy - 19260 - Digital1 
//Ejercicio 05

module testbench();

 reg A1,B1,C1;
 wire out1,out2,out3;

simplificada s1(A1,B1,C1,out1);
SOP sop1(A1,B1,C1,out2);
POS pos1(A1,B1,C1,out3);

//----------------------------------------------------------------
 //TABLA de ecuacion simplificada
 initial begin
 $display("Tabla de ecuacion simplificada - Ejercicio 05");
 $display("Armado | Ventana/Puerta | Movimiento || Alarma/Luces");
 $display("-------|----------------|------------||-------------");
 $monitor("    %b      |       %b        |    %b       ||     %b ", A1,B1,C1,out1); 
	A1=0;B1=0;C1=0;
 #1 A1=0;B1=0;C1=1;
 #1 A1=0;B1=1;C1=0; 	
 #1 A1=0;B1=1;C1=1;
 #1 A1=1;B1=0;C1=0;
 #1 A1=1;B1=0;C1=1;
 #1 A1=1;B1=1;C1=0;
 #1 A1=1;B1=1;C1=1;
 end
 //----------------------------------------------------------------
 //TABLA de ecuacion SOP
 initial begin
 #9
 $display("\n");
 $display("Tabla de ecuacion SOP - Ejercicio 05");
 $display("Armado | Ventana/Puerta | Movimiento || Alarma/Luces");
 $display("-------|----------------|------------||-------------");
 $monitor("  %b      |       %b        |    %b       ||     %b ", A1,B1,C1,out2); 
	A1=0;B1=0;C1=0;
 #1 A1=0;B1=0;C1=1;
 #1 A1=0;B1=1;C1=0; 	
 #1 A1=0;B1=1;C1=1;
 #1 A1=1;B1=0;C1=0;
 #1 A1=1;B1=0;C1=1;
 #1 A1=1;B1=1;C1=0;
 #1 A1=1;B1=1;C1=1;
 end
 //----------------------------------------------------------------
 //TABLA de ecuacion POS
 initial begin
 #17
 $display("\n");
 $display("Tabla de ecuacion POS - Ejercicio 05");
 $display("Armado | Ventana/Puerta | Movimiento || Alarma/Luces");
 $display("-------|----------------|------------||-------------");
 $monitor("    %b      |       %b        |    %b       ||     %b ", A1,B1,C1,out3); 
	A1=0;B1=0;C1=0;
 #1 A1=0;B1=0;C1=1;
 #1 A1=0;B1=1;C1=0; 	
 #1 A1=0;B1=1;C1=1;
 #1 A1=1;B1=0;C1=0;
 #1 A1=1;B1=0;C1=1;
 #1 A1=1;B1=1;C1=0;
 #1 A1=1;B1=1;C1=1;
 end
  
  initial 
 #100 $finish;
 
 initial begin 
 $dumpfile("Ejercicio05_tb.vcd");
 $dumpvars(0,testbench);
 end
 
 
 endmodule

Lab4/EJERCICIO 05/Ejercicio05_tb.vcd
$date
	Sat Aug 08 23:15:57 2020
$end
$version
	Icarus Verilog
$end
$timescale
	1ps
$end
$scope module testbench $end
$var wire 1 ! out3 $end
$var wire 1 " out2 $end
$var wire 1 # out1 $end
$var reg 1 $ A1 $end
$var reg 1 % B1 $end
$var reg 1 & C1 $end
$scope module pos1 $end
$var wire 1 $ A $end
$var wire 1 % B $end
$var wire 1 & C $end
$var wire 1 ! out3 $end
$upscope $end
$scope module s1 $end
$var wire 1 $ A $end
$var wire 1 % B $end
$var wire 1 & C $end
$var wire 1 # out1 $end
$var wire 1 ' wBn $end
$var wire 1 ( wa1 $end
$var wire 1 ) wa2 $end
$upscope $end
$scope module sop1 $end
$var wire 1 $ A $end
$var wire 1 % B $end
$var wire 1 & C $end
$var wire 1 " out2 $end
$upscope $end
$upscope $end
$enddefinitions $end
#0
$dumpvars
0)
0(
1'
0&
0%
0$
0#
0"
0!
$end
#1
1&
#2
0'
0&
1%
#3
1&
#4
1"
1!
1#
1(
1'
0&
0%
1$
#5
1)
1&
#6
0!
0"
0#
0(
0)
0'
0&
1%
#7
1!
1#
1"
1)
1&
#9
0!
0"
0#
1'
0)
0&
0%
0$
#10
1&
#11
0'
0&
1%
#12
1&
#13
1"
1!
1#
1(
1'
0&
0%
1$
#14
1)
1&
#15
0!
0"
0#
0(
0)
0'
0&
1%
#16
1!
1#
1"
1)
1&
#17
0!
0"
0#
1'
0)
0&
0%
0$
#18
1&
#19
0'
0&
1%
#20
1&
#21
1"
1!
1#
1(
1'
0&
0%
1$
#22
1)
1&
#23
0!
0"
0#
0(
0)
0'
0&
1%
#24
1!
1#
1"
1)
1&
